homelab_node_red_backup/__init__.py
homelab_node_red_backup/__main__.py
homelab_node_red_backup/handler/__init__.py
homelab_node_red_backup/handler/backup.py
homelab_node_red_backup/handler/check.py
homelab_node_red_backup/handler/flows.py
homelab_node_red_backup/handler/restore.py
homelab_node_red_backup-2.1.0.dist-info/LICENSE.md
homelab_node_red_backup-2.1.0.dist-info/METADATA
homelab_node_red_backup-2.1.0.dist-info/WHEEL
homelab_node_red_backup-2.1.0.dist-info/entry_points.txt
homelab_node_red_backup-2.1.0.dist-info/RECORD
