Metadata-Version: 2.3
Name: homelab-node-red-backup
Version: 2.1.0
Summary: Backup and Restore for Node-RED.
License: MIT
Keywords: node-red,homelab
Author: Daniel Muehlbachler-Pietrzykowski
Author-email: daniel.muehlbachler@niftyside.io
Requires-Python: >=3.12,<4.0
Classifier: Development Status :: 5 - Production/Stable
Classifier: Intended Audience :: Developers
Classifier: License :: OSI Approved :: MIT License
Classifier: Operating System :: OS Independent
Classifier: Programming Language :: Python :: 3
Classifier: Programming Language :: Python :: 3.12
Classifier: Programming Language :: Python :: 3.13
Classifier: Topic :: Home Automation
Requires-Dist: click (>=8.1.3,<9.0.0)
Requires-Dist: requests (>=2.31.0,<3.0.0)
Project-URL: Repository, https://github.com/muhlba91/onyx-client
